dirbrowser/dirbrowser.py
dirbrowser/__init__.py
dirbrowser-1.0a3.dist-info/DESCRIPTION.rst
dirbrowser-1.0a3.dist-info/METADATA
dirbrowser-1.0a3.dist-info/metadata.json
dirbrowser-1.0a3.dist-info/RECORD
dirbrowser-1.0a3.dist-info/top_level.txt
dirbrowser-1.0a3.dist-info/WHEEL
