Metadata-Version: 2.0
Name: dirbrowser
Version: 1.0a3
Summary: Command line based directory browser
Home-page: https://github.com/campenr/dirbrowser
Author: Richard Campen
Author-email: richard@campen.co
License: BSD License
